COPYING
MANIFEST.in
README.md
RELEASE-VERSION
SConstruct
pavement.py
paver-minilib.zip
setup.py
version.py
pulse_counter_rpc/__init__.py
pulse_counter_rpc/config.py
pulse_counter_rpc/node.py
pulse_counter_rpc/proxy.py
pulse_counter_rpc.egg-info/PKG-INFO
pulse_counter_rpc.egg-info/SOURCES.txt
pulse_counter_rpc.egg-info/dependency_links.txt
pulse_counter_rpc.egg-info/pbr.json
pulse_counter_rpc.egg-info/requires.txt
pulse_counter_rpc.egg-info/top_level.txt
pulse_counter_rpc/Arduino/library/PulseCounterRpc.zip
pulse_counter_rpc/Arduino/library/PulseCounterRpc/library.properties
pulse_counter_rpc/Arduino/library/PulseCounterRpc/src/PulseCounterRpc.h
pulse_counter_rpc/Arduino/library/PulseCounterRpc/src/PulseCounterRpc/CommandProcessor.h
pulse_counter_rpc/Arduino/library/PulseCounterRpc/src/PulseCounterRpc/Commands.h
pulse_counter_rpc/Arduino/library/PulseCounterRpc/src/PulseCounterRpc/Properties.h
pulse_counter_rpc/Arduino/library/PulseCounterRpc/src/PulseCounterRpc/config_pb.c
pulse_counter_rpc/Arduino/library/PulseCounterRpc/src/PulseCounterRpc/config_pb.h
pulse_counter_rpc/Arduino/pulse_counter_rpc/Node.cpp
pulse_counter_rpc/Arduino/pulse_counter_rpc/Node.h
pulse_counter_rpc/Arduino/pulse_counter_rpc/Node.h~
pulse_counter_rpc/Arduino/pulse_counter_rpc/NodeCommandProcessor.h
pulse_counter_rpc/Arduino/pulse_counter_rpc/RPCBuffer.h
pulse_counter_rpc/Arduino/pulse_counter_rpc/RPCBuffer.ht
pulse_counter_rpc/Arduino/pulse_counter_rpc/SConscript
pulse_counter_rpc/Arduino/pulse_counter_rpc/SimpleTimer.cpp
pulse_counter_rpc/Arduino/pulse_counter_rpc/SimpleTimer.h
pulse_counter_rpc/Arduino/pulse_counter_rpc/config.options
pulse_counter_rpc/Arduino/pulse_counter_rpc/config.proto
pulse_counter_rpc/Arduino/pulse_counter_rpc/pulse_counter_rpc.ino
pulse_counter_rpc/Arduino/pulse_counter_rpc/pulse_counter_rpc_config_validate.h
pulse_counter_rpc/Arduino/pulse_counter_rpc/pulse_counter_rpc_state_validate.h
pulse_counter_rpc/bin/__init__.py
pulse_counter_rpc/bin/upload.py
pulse_counter_rpc/firmware/mega2560/pulse_counter_rpc.hex
pulse_counter_rpc/firmware/uno/pulse_counter_rpc.hex