Metadata-Version: 1.0
Name: pulse-counter-rpc
Version: 0.1.post22
Summary: Arduino-based pulse counting firmware and Python driver.
Home-page: http://github.com/wheeler-microfluidics/pulse-counter-rpc.git
Author: Christian Fobel
Author-email: christian@fobel.net
License: GPLv2
Platform: UNKNOWN
